pyntual/__init__.py
pyntual/pyntual.py
pyntual/api/__init__.py
pyntual/api/api.py
pyntual-0.2.3.dist-info/AUTHORS.rst
pyntual-0.2.3.dist-info/LICENSE
pyntual-0.2.3.dist-info/METADATA
pyntual-0.2.3.dist-info/WHEEL
pyntual-0.2.3.dist-info/top_level.txt
pyntual-0.2.3.dist-info/RECORD
