Metadata-Version: 2.1
Name: pyntual
Version: 0.2.3
Summary: Fintual API Python client.
Home-page: https://github.com/vlizanae/pyntual
Author: Vicente Lizana Estivill
Author-email: v.lizana.e@gmail.com
License: MIT license
Keywords: pyntual
Platform: UNKNOWN
Classifier: Development Status :: 2 - Pre-Alpha
Classifier: Intended Audience :: Developers
Classifier: License :: OSI Approved :: MIT License
Classifier: Natural Language :: English
Classifier: Programming Language :: Python :: 3
Classifier: Programming Language :: Python :: 3.6
Classifier: Programming Language :: Python :: 3.7
Classifier: Programming Language :: Python :: 3.8
Requires-Python: >=3.6
Requires-Dist: pandas (==1.1.2)
Requires-Dist: requests (==2.24.0)
